hash_password.py
psgspecialelements.py
psgspecialelements-1.0.3.data/data/config/img/table_arrow9_transparent_64.ico
psgspecialelements-1.0.3.dist-info/METADATA
psgspecialelements-1.0.3.dist-info/WHEEL
psgspecialelements-1.0.3.dist-info/top_level.txt
psgspecialelements-1.0.3.dist-info/RECORD
